{
  "champions": [
    {
      "cost": 3,
      "name": "Alistar",
      "traits": [
        "Ox Force",
        "Mascot",
        "Aegis"
      ]
    },
    {
      "cost": 2,
      "name": "Annie",
      "traits": [
        "Gadgeteen",
        "Ox Force",
        "Spellslinger"
      ]
    },
    {
      "cost": 5,
      "name": "Aphelios",
      "traits": [
        "Ox Force",
        "Sureshot",
        "Arsenal"
      ]
    },
    {
      "cost": 1,
      "name": "Ashe",
      "traits": [
        "LaserCorps",
        "Recon"
      ]
    },
    {
      "cost": 4,
      "name": "Aurelion Sol",
      "traits": [
        "Threat",
        "-"
      ]
    },
    {
      "cost": 4,
      "name": "Belveth",
      "traits": [
        "Threat",
        "-"
      ]
    },
    {
      "cost": 1,
      "name": "Blitzcrank",
      "traits": [
        "A.D.M.I.N.",
        "Brawler"
      ]
    },
    {
      "cost": 2,
      "name": "Camille",
      "traits": [
        "A.D.M.I.N.",
        "Renegade"
      ]
    },
    {
      "cost": 3,
      "name": "Chogath",
      "traits": [
        "Threat",
        "-"
      ]
    },
    {
      "cost": 2,
      "name": "Draven",
      "traits": [
        "Mecha: PRIME",
        "Ace"
      ]
    },
    {
      "cost": 4,
      "name": "Ekko",
      "traits": [
        "Star Guardian",
        "Prankster",
        "Aegis"
      ]
    },
    {
      "cost": 2,
      "name": "Ezreal",
      "traits": [
        "The Underground",
        "Recon"
      ]
    },
    {
      "cost": 5,
      "name": "Fiddlesticks",
      "traits": [
        "Corrupted",
        "Threat",
        "-"
      ]
    },
    {
      "cost": 2,
      "name": "Fiora",
      "traits": [
        "Ox Force",
        "Duelist"
      ]
    },
    {
      "cost": 1,
      "name": "Galio",
      "traits": [
        "Civilian",
        "Mascot"
      ]
    },
    {
      "cost": 1,
      "name": "Gangplank",
      "traits": [
        "Supers",
        "Duelist"
      ]
    },
    {
      "cost": 5,
      "name": "Janna",
      "traits": [
        "Civilian",
        "Forecaster",
        "Spellslinger"
      ]
    },
    {
      "cost": 3,
      "name": "Jax",
      "traits": [
        "Mecha: PRIME",
        "Brawler"
      ]
    },
    {
      "cost": 2,
      "name": "Jinx",
      "traits": [
        "Anima Squad",
        "Prankster"
      ]
    },
    {
      "cost": 3,
      "name": "Kaisa",
      "traits": [
        "Star Guardian",
        "Recon"
      ]
    },
    {
      "cost": 1,
      "name": "Kayle",
      "traits": [
        "The Underground",
        "Duelist"
      ]
    },
    {
      "cost": 3,
      "name": "Leblanc",
      "traits": [
        "A.D.M.I.N.",
        "Spellslinger",
        "Hacker"
      ]
    },
    {
      "cost": 2,
      "name": "Lee Sin",
      "traits": [
        "Supers",
        "Heart",
        "Brawler"
      ]
    },
    {
      "cost": 5,
      "name": "Leona",
      "traits": [
        "Mecha: PRIME",
        "Renegade",
        "Aegis"
      ]
    },
    {
      "cost": 1,
      "name": "Lulu",
      "traits": [
        "Gadgeteen",
        "Heart"
      ]
    },
    {
      "cost": 1,
      "name": "Lux",
      "traits": [
        "Star Guardian",
        "Spellslinger"
      ]
    },
    {
      "cost": 2,
      "name": "Malphite",
      "traits": [
        "Supers",
        "Mascot"
      ]
    },
    {
      "cost": 4,
      "name": "Miss Fortune",
      "traits": [
        "Anima Squad",
        "Ace"
      ]
    },
    {
      "cost": 5,
      "name": "Mordekaiser",
      "traits": [
        "LaserCorps",
        "Ace"
      ]
    },
    {
      "cost": 1,
      "name": "Nasus",
      "traits": [
        "Anima Squad",
        "Mascot"
      ]
    },
    {
      "cost": 3,
      "name": "Nilah",
      "traits": [
        "Star Guardian",
        "Duelist"
      ]
    },
    {
      "cost": 5,
      "name": "Nunu",
      "traits": [
        "Gadgeteen",
        "Mascot"
      ]
    },
    {
      "cost": 1,
      "name": "Poppy",
      "traits": [
        "Gadgeteen",
        "Defender"
      ]
    },
    {
      "cost": 3,
      "name": "Rammus",
      "traits": [
        "Threat",
        "-"
      ]
    },
    {
      "cost": 2,
      "name": "Rell",
      "traits": [
        "Star Guardian",
        "Defender"
      ]
    },
    {
      "cost": 1,
      "name": "Renekton",
      "traits": [
        "LaserCorps",
        "Brawler"
      ]
    },
    {
      "cost": 3,
      "name": "Riven",
      "traits": [
        "Anima Squad",
        "Brawler",
        "Defender"
      ]
    },
    {
      "cost": 4,
      "name": "Samira",
      "traits": [
        "The Underground",
        "Sureshot",
        "Ace"
      ]
    },
    {
      "cost": 4,
      "name": "Sejuani",
      "traits": [
        "LaserCorps",
        "Brawler"
      ]
    },
    {
      "cost": 3,
      "name": "Senna",
      "traits": [
        "LaserCorps",
        "Sureshot"
      ]
    },
    {
      "cost": 4,
      "name": "Sett",
      "traits": [
        "Mecha: PRIME",
        "Defender"
      ]
    },
    {
      "cost": 2,
      "name": "Sivir",
      "traits": [
        "Civilian",
        "Sureshot"
      ]
    },
    {
      "cost": 3,
      "name": "Sona",
      "traits": [
        "The Underground",
        "Spellslinger",
        "Heart"
      ]
    },
    {
      "cost": 4,
      "name": "Soraka",
      "traits": [
        "A.D.M.I.N.",
        "Heart"
      ]
    },
    {
      "cost": 1,
      "name": "Sylas",
      "traits": [
        "Anima Squad",
        "Renegade"
      ]
    },
    {
      "cost": 5,
      "name": "Syndra",
      "traits": [
        "Star Guardian",
        "Heart"
      ]
    },
    {
      "cost": 4,
      "name": "Taliyah",
      "traits": [
        "Star Guardian",
        "Spellslinger"
      ]
    },
    {
      "cost": 1,
      "name": "Talon",
      "traits": [
        "Ox Force",
        "Renegade"
      ]
    },
    {
      "cost": 5,
      "name": "Urgot",
      "traits": [
        "Threat",
        "-"
      ]
    },
    {
      "cost": 3,
      "name": "Vayne",
      "traits": [
        "Anima Squad",
        "Recon",
        "Duelist"
      ]
    },
    {
      "cost": 3,
      "name": "Velkoz",
      "traits": [
        "Threat",
        "-"
      ]
    },
    {
      "cost": 2,
      "name": "Vi",
      "traits": [
        "The Underground",
        "Brawler",
        "Aegis"
      ]
    },
    {
      "cost": 4,
      "name": "Viego",
      "traits": [
        "Ox Force",
        "Renegade"
      ]
    },
    {
      "cost": 1,
      "name": "Wukong",
      "traits": [
        "Mecha: PRIME",
        "Defender"
      ]
    },
    {
      "cost": 2,
      "name": "Yasuo",
      "traits": [
        "LaserCorps",
        "Duelist"
      ]
    },
    {
      "cost": 2,
      "name": "Yuumi",
      "traits": [
        "Star Guardian",
        "Mascot",
        "Heart"
      ]
    },
    {
      "cost": 4,
      "name": "Zac",
      "traits": [
        "Threat",
        "-"
      ]
    },
    {
      "cost": 4,
      "name": "Zed",
      "traits": [
        "LaserCorps",
        "Duelist",
        "Hacker"
      ]
    },
    {
      "cost": 3,
      "name": "Zoe",
      "traits": [
        "Gadgeteen",
        "Prankster",
        "Hacker"
      ]
    }
  ],
  "traits": [
    {
      "name": "A.D.M.I.N.",
      "levels": [
        2,
        4,
        6
      ]
    },
    {
      "name": "Anima Squad",
      "levels": [
        3,
        5,
        7
      ]
    },
    {
      "name": "Civilian",
      "levels": [
        1,
        2,
        3
      ]
    },
    {
      "name": "Corrupted",
      "levels": [
        1
      ]
    },
    {
      "name": "Gadgeteen",
      "levels": [
        3,
        5
      ]
    },
    {
      "name": "LaserCorps",
      "levels": [
        3,
        6,
        9
      ]
    },
    {
      "name": "Mecha: PRIME",
      "levels": [
        3,
        5
      ]
    },
    {
      "name": "Ox Force",
      "levels": [
        2,
        4,
        6
      ]
    },
    {
      "name": "Star Guardian",
      "levels": [
        3,
        5,
        7,
        9
      ]
    },
    {
      "name": "Supers",
      "levels": [
        3
      ]
    },
    {
      "name": "Threat",
      "levels": [
        1
      ]
    },
    {
      "name": "The Underground",
      "levels": [
        3,
        5
      ]
    },
    {
      "name": "Ace",
      "levels": [
        1,
        4
      ]
    },
    {
      "name": "Aegis",
      "levels": [
        2,
        3,
        4,
        5
      ]
    },
    {
      "name": "Arsenal",
      "levels": [
        1
      ]
    },
    {
      "name": "Brawler",
      "levels": [
        2,
        4,
        6,
        8
      ]
    },
    {
      "name": "Defender",
      "levels": [
        2,
        4,
        6
      ]
    },
    {
      "name": "Duelist",
      "levels": [
        2,
        4,
        6,
        8
      ]
    },
    {
      "name": "Forecaster",
      "levels": [
        1
      ]
    },
    {
      "name": "Hacker",
      "levels": [
        2,
        3,
        4
      ]
    },
    {
      "name": "Heart",
      "levels": [
        2,
        4,
        6
      ]
    },
    {
      "name": "Mascot",
      "levels": [
        2,
        4,
        6,
        8
      ]
    },
    {
      "name": "Prankster",
      "levels": [
        2,
        3
      ]
    },
    {
      "name": "Recon",
      "levels": [
        2,
        3,
        4
      ]
    },
    {
      "name": "Renegade",
      "levels": [
        3,
        6
      ]
    },
    {
      "name": "Spellslinger",
      "levels": [
        2,
        4,
        6
      ]
    },
    {
      "name": "Sureshot",
      "levels": [
        2,
        4
      ]
    }
  ]
}